debug2/__init__.py
debug2/debug2.py
debug2-0.1.0.dist-info/LICENSE
debug2-0.1.0.dist-info/METADATA
debug2-0.1.0.dist-info/WHEEL
debug2-0.1.0.dist-info/top_level.txt
debug2-0.1.0.dist-info/RECORD
