Metadata-Version: 2.1
Name: debug2
Version: 0.1.0
Summary: A debug Python package
License-File: LICENSE
